StratLab/__init__.py
StratLab/backtest_stats.py
StratLab/conditions.py
StratLab/data.py
StratLab/holdings.py
StratLab/indicators.py
StratLab/plots.py
StratLab/simulate.py
StratLab/user_desktop.py
StratLab/version.py
StratLab/xcel.py
StratLab/_IndicatorLib/__init__.py
StratLab/_IndicatorLib/ema.py
StratLab/_IndicatorLib/macd.py
StratLab/_IndicatorLib/rsi.py
StratLab/_IndicatorLib/sar.py
StratLab/_IndicatorLib/sma.py
StratLab/_IndicatorLib/sma_deviation.py
StratLab-1.0.24.dist-info/METADATA
StratLab-1.0.24.dist-info/WHEEL
StratLab-1.0.24.dist-info/top_level.txt
StratLab-1.0.24.dist-info/RECORD
