Metadata-Version: 2.1
Name: StratLab
Version: 1.0.24
Summary: Python library dedicated to simplifying the process of backtesting complex stock market strategies.
Home-page: https://github.com/rstickles16/StratLab
Author: Robert Stickles
Author-email: rstickles16@outlook.com
License: MIT
Classifier: Programming Language :: Python :: 3
Classifier: License :: OSI Approved :: MIT License
Classifier: Operating System :: OS Independent
Requires-Python: >=3.6
Requires-Dist: datetime
Requires-Dist: pandas
Requires-Dist: numpy
Requires-Dist: yfinance
Requires-Dist: matplotlib
